gbfs_analytics/__init__.py
gbfs_analytics/gbfs_manager.py
gbfs_analytics/gbfs_timeseries.py
gbfs_analytics/gbfsfeed.py
gbfs_analytics-0.1.6.dist-info/METADATA
gbfs_analytics-0.1.6.dist-info/WHEEL
gbfs_analytics-0.1.6.dist-info/RECORD
