Metadata-Version: 2.1
Name: gbfs_analytics
Version: 0.1.6
Summary: Tools for polling and analytics on Generalized Bikeshare Feed Specification (GBFS) v2.3 feeds
License: Apache-2.0
Author: Transit Ventures Limited
Author-email: hello@bikewatch.nyc
Requires-Python: >=3.11,<3.12
Classifier: License :: OSI Approved :: Apache Software License
Classifier: Operating System :: OS Independent
Classifier: Programming Language :: Python :: 3
Classifier: Programming Language :: Python :: 3.11
Requires-Dist: requests (>=2.28.2,<3.0.0)
Requires-Dist: schedule (>=1.0.0,<2.0.0)
Project-URL: homepage, https://www.bikewatch.nyc
Project-URL: repository, https://github.com/pjlanger1/gbfs_analytics
